llm_mem/__init__.py
llm_mem/cli.py
llm_mem/llm_memory_calculator.py
llm_mem-0.1.1.dist-info/METADATA
llm_mem-0.1.1.dist-info/WHEEL
llm_mem-0.1.1.dist-info/entry_points.txt
llm_mem-0.1.1.dist-info/licenses/LICENSE
llm_mem-0.1.1.dist-info/RECORD
