Metadata-Version: 2.4
Name: llm-mem
Version: 0.1.1
Summary: lllm-mem is a lightweight Python CLI tool designed to calculate the GPU VRAM requirements for models on Hugging Face
Author-email: Mathias Nielsen <mathiasesn1@gmail.com>
Maintainer-email: Mathias Nielsen <mathiasesn1@gmail.com>
License: MIT License
License-File: LICENSE
Requires-Python: >=3.10
Requires-Dist: huggingface-hub>=0.30.1
Requires-Dist: python-dotenv>=1.1.0
Requires-Dist: rich>=14.0.0
Requires-Dist: tqdm>=4.67.1
